pydantic_kedro/__init__.py
pydantic_kedro/_dict_io.py
pydantic_kedro/_internals.py
pydantic_kedro/_local_caching.py
pydantic_kedro/_pydantic.py
pydantic_kedro/models.py
pydantic_kedro/py.typed
pydantic_kedro/utils.py
pydantic_kedro/version.py
pydantic_kedro/datasets/__init__.py
pydantic_kedro/datasets/auto.py
pydantic_kedro/datasets/folder.py
pydantic_kedro/datasets/json.py
pydantic_kedro/datasets/yaml.py
pydantic_kedro/datasets/zip.py
pydantic_kedro-0.8.0.dist-info/LICENSE
pydantic_kedro-0.8.0.dist-info/METADATA
pydantic_kedro-0.8.0.dist-info/WHEEL
pydantic_kedro-0.8.0.dist-info/top_level.txt
pydantic_kedro-0.8.0.dist-info/RECORD
