Metadata-Version: 2.1
Name: pydantic-kedro
Version: 0.8.0
Summary: Kedro
License: MIT License
Project-URL: github, https://github.com/NowanIlfideme/pydantic-kedro
Keywords: pydantic,kedro,fsspec
Classifier: Programming Language :: Python :: 3
Classifier: Development Status :: 2 - Pre-Alpha
Classifier: Intended Audience :: Developers
Classifier: License :: OSI Approved :: MIT License
Classifier: Topic :: Software Development
Classifier: Typing :: Typed
Requires-Python: >=3.9
License-File: LICENSE
Requires-Dist: pydantic <3,>=1.10.0
Requires-Dist: pydantic-yaml >=1.3.0
Requires-Dist: ruamel-yaml <0.18
Requires-Dist: kedro <0.20,>=0.19.3
Requires-Dist: kedro-datasets >=2.1.0
Requires-Dist: fsspec
Provides-Extra: dev
Requires-Dist: setuptools >=61.0.0 ; extra == 'dev'
Requires-Dist: setuptools-scm[toml] >=6.2 ; extra == 'dev'
Requires-Dist: pre-commit ==3.6.0 ; extra == 'dev'
Requires-Dist: black ==23.11.0 ; extra == 'dev'
Requires-Dist: isort ==5.12.0 ; extra == 'dev'
Requires-Dist: ruff ==0.3.4 ; extra == 'dev'
Requires-Dist: mypy ==1.9.0 ; extra == 'dev'
Requires-Dist: pytest ==7.4.2 ; extra == 'dev'
Requires-Dist: pandas <2.2.0,>=1.5.3 ; extra == 'dev'
Requires-Dist: pyspark <3.6.0,>=3.4.1 ; extra == 'dev'
Requires-Dist: kedro-datasets[pandas,spark] ; extra == 'dev'
Requires-Dist: pandas-stubs ; extra == 'dev'
Provides-Extra: docs
Requires-Dist: mkdocs ; extra == 'docs'
Requires-Dist: mkdocs-material ; extra == 'docs'
Requires-Dist: mkdocstrings[python] ; extra == 'docs'
Requires-Dist: pymdown-extensions ; extra == 'docs'
Requires-Dist: pygments ; extra == 'docs'
